{
  "frame0": [
    {
      "clusters_x": [
        229.345,
        743.46
      ],
      "clusters_y": [
        75.555,
        70.3
      ],
      "clusters_text": [
        [
          "London",
          "London"
        ],
        [
          "Nov<sw-ex>embe</sw-ex>r",
          "Nov<sw-sup>r</sw-sup>"
        ],
        [
          "19<sw-sup>th</sw-sup>",
          "19<sw-sup>th</sw-sup>"
        ],
        [
          "1713",
          "1713"
        ]
      ],
      "number_views": 2,
      "consensus_score": 1.75,
      "consensus_text": "London Nov<sw-ex>embe</sw-ex>r 19<sw-sup>th</sw-sup> 1713",
      "line_slope": -0.6127575449941545,
      "slope_label": 0,
      "gutter_label": 1,
      "gold_standard": [
        false,
        false
      ],
      "extract_index": [
        1,
        5
      ],
      "user_ids": [
        429539.0,
        1708223.0
      ],
      "low_consensus": true
    },
    {
      "clusters_x": [
        93.185,
        915.415
      ],
      "clusters_y": [
        119.17,
        116.825
      ],
      "clusters_text": [
        [
          "Since",
          "Since"
        ],
        [
          "our",
          "our"
        ],
        [
          "last",
          "last"
        ],
        [
          "came",
          "came"
        ],
        [
          "in",
          "in"
        ],
        [
          "<brev-y>th</brev-y><sl>e</sl>",
          "<brev-y>th</brev-y><sl>e</sl>"
        ],
        [
          "Holland",
          "Holl<sw-sup>d</sw-sup>"
        ],
        [
          "&",
          "&"
        ],
        [
          "fflanders",
          "fflanders"
        ],
        [
          "Mailes",
          "Mailes"
        ]
      ],
      "number_views": 2,
      "consensus_score": 1.9,
      "consensus_text": "Since our last came in <brev-y>th</brev-y><sl>e</sl> Holland & fflanders Mailes",
      "line_slope": -0.6127575449941545,
      "slope_label": 0,
      "gutter_label": 1,
      "gold_standard": [
        false,
        false
      ],
      "extract_index": [
        2,
        6
      ],
      "user_ids": [
        429539.0,
        1708223.0
      ],
      "low_consensus": true
    },
    {
      "clusters_x": [
        101.45666666666666,
        926.0333333333334
      ],
      "clusters_y": [
        172.71333333333334,
        163.96
      ],
      "clusters_text": [
        [
          "w<sw-ex>i</sw-ex><sl>th</sl>",
          "w<sw-ex>i</sw-ex><sl>th</sl>",
          "w<sw-ex>i</sw-ex><sl>th</sl>"
        ],
        [
          "<brev-y>th</brev-y><sl>e</sl>",
          "<brev-y>th</brev-y><sl>e</sl>",
          "<brev-y>th</brev-y><sl>e</sl>"
        ],
        [
          "follow<sw-ex>ing</sw-ex>",
          "foll<sw-ex>owing</sw-ex>",
          "foll"
        ],
        [
          "news",
          "News",
          "News"
        ],
        [
          "-",
          "-",
          "-"
        ],
        [
          "from",
          "from",
          "from"
        ],
        [
          "Warsaw",
          "Warsaw",
          "Warsaw"
        ],
        [
          "<brev-y>th</brev-y><sw-ex>a</sw-ex><sl>t</sl>",
          "<brev-y>th</brev-y><sw-ex>a</sw-ex><sl>t</sl>",
          "<brev-y>th</brev-y><sw-ex>a</sw-ex><sl>t</sl>"
        ],
        [
          "they",
          "they",
          "they"
        ],
        [
          "have",
          "have",
          "have"
        ],
        [
          "Re<sw-ex>ceiv</sw-ex>ed",
          "Rec<sw-ex>eive</sw-ex>d",
          "Reced"
        ],
        [
          "Advices",
          "Advices",
          "Advices"
        ]
      ],
      "number_views": 3,
      "consensus_score": 2.5833333333333335,
      "consensus_text": "w<sw-ex>i</sw-ex><sl>th</sl> <brev-y>th</brev-y><sl>e</sl> follow<sw-ex>ing</sw-ex> News - from Warsaw <brev-y>th</brev-y><sw-ex>a</sw-ex><sl>t</sl> they have Re<sw-ex>ceiv</sw-ex>ed Advices",
      "line_slope": -0.6127575449941545,
      "slope_label": 0,
      "gutter_label": 1,
      "gold_standard": [
        false,
        false,
        false
      ],
      "extract_index": [
        3,
        3,
        7
      ],
      "user_ids": [
        null,
        429539.0,
        1708223.0
      ],
      "low_consensus": true
    },
    {
      "clusters_x": [
        99.8,
        920.0433333333334
      ],
      "clusters_y": [
        221.22000000000003,
        220.9
      ],
      "clusters_text": [
        [
          "from",
          "from",
          "from"
        ],
        [
          "Turley",
          "Turkey",
          "Turkey"
        ],
        [
          "<brev-y>th</brev-y><sw-ex>a</sw-ex><sl>t</sl>",
          "<brev-y>th</brev-y><sw-ex>a</sw-ex><sl>t</sl>",
          "<brev-y>th</brev-y><sw-ex>a</sw-ex><sl>t</sl>"
        ],
        [
          "<brev-y>th</brev-y><sl>e</sl>",
          "<brev-y>th</brev-y><sl>e</sl>",
          "<brev-y>th</brev-y><sl>e</sl>"
        ],
        [
          "New",
          "New",
          "New"
        ],
        [
          "Grand",
          "Grand",
          "Grand"
        ],
        [
          "Vizier",
          "Vizier",
          "Vizier"
        ],
        [
          "has",
          "has",
          "has"
        ],
        [
          "been",
          "been",
          "been"
        ],
        [
          "privately",
          "privately",
          "privately"
        ]
      ],
      "number_views": 3,
      "consensus_score": 2.9,
      "consensus_text": "from Turkey <brev-y>th</brev-y><sw-ex>a</sw-ex><sl>t</sl> <brev-y>th</brev-y><sl>e</sl> New Grand Vizier has been privately",
      "line_slope": -0.6127575449941545,
      "slope_label": 0,
      "gutter_label": 1,
      "gold_standard": [
        false,
        false,
        false
      ],
      "extract_index": [
        4,
        4,
        4
      ],
      "user_ids": [
        null,
        429539.0,
        1708223.0
      ],
      "low_consensus": true
    },
    {
      "clusters_x": [
        97.97666666666667,
        913.8733333333333
      ],
      "clusters_y": [
        275.45,
        270.07
      ],
      "clusters_text": [
        [
          "strangled",
          "strangled",
          "Strangled"
        ],
        [
          "for",
          "for",
          "for"
        ],
        [
          "being",
          "being",
          "being"
        ],
        [
          "in",
          "in",
          "in"
        ],
        [
          "<brev-y>th</brev-y><sl>e</sl>",
          "<brev-y>th</brev-y><sl>e</sl>",
          "<brev-y>th</brev-y><sl>e</sl>"
        ],
        [
          "Jnterest",
          "Interest",
          "Interest"
        ],
        [
          "of",
          "of",
          "of"
        ],
        [
          "<brev-y>th</brev-y><sl>e</sl>",
          "<brev-y>th</brev-y><sl>e</sl>",
          "<brev-y>th</brev-y><sl>e</sl>"
        ],
        [
          "Czar",
          "Czar",
          "Czar"
        ],
        [
          "&",
          "&",
          "&"
        ],
        [
          "King",
          "King",
          "King"
        ]
      ],
      "number_views": 3,
      "consensus_score": 2.8181818181818183,
      "consensus_text": "strangled for being in <brev-y>th</brev-y><sl>e</sl> Interest of <brev-y>th</brev-y><sl>e</sl> Czar & King",
      "line_slope": -0.6127575449941545,
      "slope_label": 0,
      "gutter_label": 1,
      "gold_standard": [
        false,
        false,
        false
      ],
      "extract_index": [
        5,
        5,
        8
      ],
      "user_ids": [
        null,
        429539.0,
        1708223.0
      ],
      "low_consensus": true
    },
    {
      "clusters_x": [
        98.37,
        925.6333333333333
      ],
      "clusters_y": [
        326.67,
        320.29999999999995
      ],
      "clusters_text": [
        [
          "Augustus",
          "Augustus",
          "Augustus"
        ],
        [
          "-",
          "-",
          "-"
        ],
        [
          "Jt",
          "It",
          "It"
        ],
        [
          "is",
          "is",
          "is"
        ],
        [
          "wrote",
          "wrote",
          "wrote"
        ],
        [
          "from",
          "from",
          "from"
        ],
        [
          "Vienna",
          "Vienna",
          "Vienna"
        ],
        [
          "<brev-y>th</brev-y><sw-ex>a</sw-ex><sl>t</sl>",
          "<brev-y>th</brev-y><sw-ex>a</sw-ex><sl>t</sl>",
          "<brev-y>th</brev-y><sw-ex>a</sw-ex><sl>t</sl>"
        ],
        [
          "<brev-y>th</brev-y><sl>e</sl>",
          "<brev-y>th</brev-y><sl>e</sl>",
          "<brev-y>th</brev-y><sl>e</sl>"
        ],
        [
          "Emperor",
          "Emperor",
          "Emperor"
        ]
      ],
      "number_views": 3,
      "consensus_score": 2.9,
      "consensus_text": "Augustus - It is wrote from Vienna <brev-y>th</brev-y><sw-ex>a</sw-ex><sl>t</sl> <brev-y>th</brev-y><sl>e</sl> Emperor",
      "line_slope": -0.6127575449941545,
      "slope_label": 0,
      "gutter_label": 1,
      "gold_standard": [
        false,
        false,
        false
      ],
      "extract_index": [
        6,
        6,
        9
      ],
      "user_ids": [
        null,
        429539.0,
        1708223.0
      ],
      "low_consensus": true
    },
    {
      "clusters_x": [
        103.02666666666666,
        911.82
      ],
      "clusters_y": [
        377.38333333333327,
        363.3033333333333
      ],
      "clusters_text": [
        [
          "holds",
          "holds",
          "holds"
        ],
        [
          "frequent",
          "frequent",
          "frequent"
        ],
        [
          "Councells",
          "Councells",
          "Councells"
        ],
        [
          "about",
          "about",
          "about"
        ],
        [
          "Recruiteing",
          "Recruiteing",
          "Recruteing"
        ],
        [
          "and",
          "and",
          "and"
        ]
      ],
      "number_views": 3,
      "consensus_score": 2.8333333333333335,
      "consensus_text": "holds frequent Councells about Recruiteing and",
      "line_slope": -0.6127575449941545,
      "slope_label": 0,
      "gutter_label": 1,
      "gold_standard": [
        false,
        false,
        false
      ],
      "extract_index": [
        7,
        7,
        10
      ],
      "user_ids": [
        null,
        429539.0,
        1708223.0
      ],
      "low_consensus": true
    },
    {
      "clusters_x": [
        103.55333333333333,
        921.6433333333333
      ],
      "clusters_y": [
        425.21000000000004,
        422.8666666666666
      ],
      "clusters_text": [
        [
          "Augmenting",
          "Augmenting",
          "Augmenting"
        ],
        [
          "of",
          "of",
          "of"
        ],
        [
          "his",
          "his",
          "his"
        ],
        [
          "fforces",
          "fforces",
          "fforces"
        ],
        [
          "ag<sw-ex>ain</sw-ex>st",
          "ag<sw-ex>ains</sw-ex>t",
          "ag<sw-sup>st"
        ],
        [
          "next",
          "next",
          "</sw-sup>next"
        ],
        [
          "Campaign",
          "Campaign",
          "Campaign"
        ]
      ],
      "number_views": 3,
      "consensus_score": 2.5714285714285716,
      "consensus_text": "Augmenting of his fforces ag<sw-ex>ain</sw-ex>st next Campaign",
      "line_slope": -0.6127575449941545,
      "slope_label": 0,
      "gutter_label": 1,
      "gold_standard": [
        false,
        false,
        false
      ],
      "extract_index": [
        8,
        8,
        11
      ],
      "user_ids": [
        null,
        429539.0,
        1708223.0
      ],
      "low_consensus": true
    },
    {
      "clusters_x": [
        98.92,
        931.4033333333333
      ],
      "clusters_y": [
        526.9866666666667,
        528.9033333333333
      ],
      "clusters_text": [
        [
          "Empire",
          "Empire",
          "empire"
        ],
        [
          "to",
          "to",
          "to"
        ],
        [
          "Exhort",
          "Exhort",
          "Exhort"
        ],
        [
          "them",
          "them",
          "them"
        ],
        [
          "to",
          "to",
          "to"
        ],
        [
          "furnish",
          "furnish",
          "furnish"
        ],
        [
          "their",
          "their",
          "their"
        ],
        [
          "full",
          "full",
          "full"
        ],
        [
          "Quota's",
          "Quota's",
          "Quotas"
        ]
      ],
      "number_views": 3,
      "consensus_score": 2.7777777777777777,
      "consensus_text": "Empire to Exhort them to furnish their full Quota's",
      "line_slope": -0.6127575449941545,
      "slope_label": 0,
      "gutter_label": 1,
      "gold_standard": [
        false,
        false,
        false
      ],
      "extract_index": [
        10,
        10,
        12
      ],
      "user_ids": [
        null,
        429539.0,
        1708223.0
      ],
      "low_consensus": true
    },
    {
      "clusters_x": [
        99.65,
        918.11
      ],
      "clusters_y": [
        582.875,
        580.065
      ],
      "clusters_text": [
        [
          "of",
          "of"
        ],
        [
          "Men",
          "Men"
        ],
        [
          "&",
          "&"
        ],
        [
          "Money,",
          "Money,"
        ],
        [
          "<brev-y>th</brev-y><sw-ex>a</sw-ex><sl>t</sl>",
          "<brev-y>th</brev-y><sw-ex>a</sw-ex><sl>t</sl>"
        ],
        [
          "his",
          "his"
        ],
        [
          "Imp<sw-ex>eria</sw-ex>ll",
          "Impll"
        ],
        [
          "Mai<sw-ex>es</sw-ex>ty",
          "Maj<sw-sup>ty</sw-sup>"
        ],
        [
          "may",
          "may"
        ],
        [
          "Act",
          "Act"
        ]
      ],
      "number_views": 2,
      "consensus_score": 1.8,
      "consensus_text": "of Men & Money, <brev-y>th</brev-y><sw-ex>a</sw-ex><sl>t</sl> his Imp<sw-ex>eria</sw-ex>ll Mai<sw-ex>es</sw-ex>ty may Act",
      "line_slope": -0.6127575449941545,
      "slope_label": 0,
      "gutter_label": 1,
      "gold_standard": [
        false,
        false
      ],
      "extract_index": [
        11,
        3
      ],
      "user_ids": [
        429539.0,
        1708223.0
      ],
      "low_consensus": true
    },
    {
      "clusters_x": [
        101.02000000000001,
        920.6949999999999
      ],
      "clusters_y": [
        632.8050000000001,
        632.73
      ],
      "clusters_text": [
        [
          "Offensively",
          "Offensively"
        ],
        [
          "ag<sw-ex>ains</sw-ex>t",
          "ag<sw-sup>st</sw-sup>"
        ],
        [
          "ffrance",
          "ffrance"
        ],
        [
          "-",
          "-"
        ],
        [
          "Letters",
          "Letters"
        ],
        [
          "from",
          "from"
        ],
        [
          "the",
          "the"
        ]
      ],
      "number_views": 2,
      "consensus_score": 1.8571428571428572,
      "consensus_text": "Offensively ag<sw-ex>ains</sw-ex>t ffrance - Letters from the",
      "line_slope": -0.6127575449941545,
      "slope_label": 0,
      "gutter_label": 1,
      "gold_standard": [
        false,
        false
      ],
      "extract_index": [
        12,
        2
      ],
      "user_ids": [
        429539.0,
        1708223.0
      ],
      "low_consensus": true
    },
    {
      "clusters_x": [
        111.455,
        920.5999999999999
      ],
      "clusters_y": [
        690.9,
        687.345
      ],
      "clusters_text": [
        [
          "ffrench",
          "ffrench"
        ],
        [
          "Camp",
          "Camp"
        ],
        [
          "before",
          "before"
        ],
        [
          "ffriburgh",
          "ffriburgh"
        ],
        [
          "say",
          "say"
        ],
        [
          "<brev-y>th</brev-y><sw-ex>a</sw-ex><sl>t</sl>",
          "<brev-y>th</brev-y><sw-ex>a</sw-ex><sl>t</sl>"
        ],
        [
          "Marsh<sw-ex>all</sw-ex>",
          "Marsh"
        ]
      ],
      "number_views": 2,
      "consensus_score": 1.8571428571428572,
      "consensus_text": "ffrench Camp before ffriburgh say <brev-y>th</brev-y><sw-ex>a</sw-ex><sl>t</sl> Marsh<sw-ex>all</sw-ex>",
      "line_slope": -0.6127575449941545,
      "slope_label": 0,
      "gutter_label": 1,
      "gold_standard": [
        false,
        false
      ],
      "extract_index": [
        13,
        13
      ],
      "user_ids": [
        429539.0,
        1708223.0
      ],
      "low_consensus": true
    },
    {
      "clusters_x": [
        104.07333333333334,
        932.1966666666667
      ],
      "clusters_y": [
        742.34,
        739.8800000000001
      ],
      "clusters_text": [
        [
          "Villars",
          "Villars",
          "Villars"
        ],
        [
          "is",
          "is",
          "is"
        ],
        [
          "highly",
          "highly",
          "highly"
        ],
        [
          "Jncensed",
          "Incensed",
          "Incensed"
        ],
        [
          "w<sw-ex>i</sw-ex><sl>th</sl>",
          "w<sw-ex>i</sw-ex><sl>th</sl>",
          "w<sw-ex>i</sw-ex><sl>th</sl>"
        ],
        [
          "<brev-y>th</brev-y><sl>e</sl>",
          "<brev-y>th</brev-y><sl>e</sl>",
          "<brev-y>th</brev-y><sl>e</sl>"
        ],
        [
          "Gov<sw-ex>e</sw-ex>rn<sw-ex>ou</sw-ex>rs",
          "Gov<sw-ex>ernor</sw-ex>s",
          "Govn<sw-sup>rs</sw-sup>"
        ],
        [
          "Refuceing",
          "Refuseing",
          "Refuseing"
        ]
      ],
      "number_views": 3,
      "consensus_score": 2.5,
      "consensus_text": "Villars is highly Incensed w<sw-ex>i</sw-ex><sl>th</sl> <brev-y>th</brev-y><sl>e</sl> Gov<sw-ex>e</sw-ex>rn<sw-ex>ou</sw-ex>rs Refuseing",
      "line_slope": -0.6127575449941545,
      "slope_label": 0,
      "gutter_label": 1,
      "gold_standard": [
        false,
        false,
        false
      ],
      "extract_index": [
        14,
        14,
        14
      ],
      "user_ids": [
        null,
        429539.0,
        1708223.0
      ],
      "low_consensus": true
    },
    {
      "clusters_x": [
        109.025,
        924.47
      ],
      "clusters_y": [
        797.7850000000001,
        794.865
      ],
      "clusters_text": [
        [
          "to",
          "to"
        ],
        [
          "surrender",
          "Surrender"
        ],
        [
          "&",
          "&"
        ],
        [
          "threatens",
          "threatens"
        ],
        [
          "to",
          "to"
        ],
        [
          "put",
          "put"
        ],
        [
          "him",
          "him"
        ],
        [
          "and",
          "and"
        ],
        [
          "the",
          "the"
        ]
      ],
      "number_views": 2,
      "consensus_score": 1.8888888888888888,
      "consensus_text": "to surrender & threatens to put him and the",
      "line_slope": -0.6127575449941545,
      "slope_label": 0,
      "gutter_label": 1,
      "gold_standard": [
        false,
        false
      ],
      "extract_index": [
        15,
        15
      ],
      "user_ids": [
        429539.0,
        1708223.0
      ],
      "low_consensus": true
    },
    {
      "clusters_x": [
        105.66666666666667,
        909.18
      ],
      "clusters_y": [
        854.3566666666667,
        849.6833333333333
      ],
      "clusters_text": [
        [
          "Garryson",
          "Garryson",
          "Garryson"
        ],
        [
          "to",
          "to",
          "to"
        ],
        [
          "<brev-y>th</brev-y><sl>e</sl>",
          "<brev-y>th</brev-y><sl>e</sl>",
          "<brev-y>th</brev-y><sl>e</sl>"
        ],
        [
          "sword",
          "sword",
          "Sword"
        ],
        [
          "-",
          "-",
          "-"
        ],
        [
          "the",
          "The",
          "the"
        ],
        [
          "Garryson",
          "Garryson",
          "Garryson"
        ],
        [
          "Consists",
          "Consists",
          "Consists"
        ]
      ],
      "number_views": 3,
      "consensus_score": 2.75,
      "consensus_text": "Garryson to <brev-y>th</brev-y><sl>e</sl> sword - the Garryson Consists",
      "line_slope": -0.6127575449941545,
      "slope_label": 0,
      "gutter_label": 1,
      "gold_standard": [
        false,
        false,
        false
      ],
      "extract_index": [
        16,
        16,
        16
      ],
      "user_ids": [
        null,
        429539.0,
        1708223.0
      ],
      "low_consensus": true
    },
    {
      "clusters_x": [
        107.55,
        917.7166666666666
      ],
      "clusters_y": [
        909.3733333333333,
        896.2966666666666
      ],
      "clusters_text": [
        [
          "of",
          "of",
          "of"
        ],
        [
          "5000",
          "5000",
          "5000"
        ],
        [
          "Men",
          "Men",
          "Men"
        ],
        [
          "-",
          "-",
          "-"
        ],
        [
          "the",
          "The",
          "The"
        ],
        [
          "said",
          "said",
          "said"
        ],
        [
          "Marsh<sw-ex>all</sw-ex>",
          "Marsh<sw-ex>all</sw-ex>",
          "Marsh"
        ],
        [
          "proposes",
          "proposes",
          "proposes"
        ],
        [
          "to",
          "to",
          "to"
        ]
      ],
      "number_views": 3,
      "consensus_score": 2.7777777777777777,
      "consensus_text": "of 5000 Men - The said Marsh<sw-ex>all</sw-ex> proposes to",
      "line_slope": -0.6127575449941545,
      "slope_label": 0,
      "gutter_label": 1,
      "gold_standard": [
        false,
        false,
        false
      ],
      "extract_index": [
        17,
        17,
        1
      ],
      "user_ids": [
        null,
        429539.0,
        1708223.0
      ],
      "low_consensus": true
    },
    {
      "clusters_x": [
        99.89,
        873.96
      ],
      "clusters_y": [
        963.01,
        958.725
      ],
      "clusters_text": [
        [
          "Arrack",
          "Attack"
        ],
        [
          "Gen<sw-ex>era</sw-ex>ll",
          "Gen<sw-sup>ll</sw-sup>"
        ],
        [
          "Vanbonns",
          "Vanbonns"
        ],
        [
          "Lines",
          "Lines"
        ],
        [
          "at",
          "at"
        ],
        [
          "Rothweil",
          "Rothweil"
        ]
      ],
      "number_views": 2,
      "consensus_score": 1.6666666666666667,
      "consensus_text": "Arrack Gen<sw-ex>era</sw-ex>ll Vanbonns Lines at Rothweil",
      "line_slope": -0.6127575449941545,
      "slope_label": 0,
      "gutter_label": 1,
      "gold_standard": [
        false,
        false
      ],
      "extract_index": [
        18,
        17
      ],
      "user_ids": [
        429539.0,
        1708223.0
      ],
      "low_consensus": true
    },
    {
      "clusters_x": [
        104.48,
        922.81
      ],
      "clusters_y": [
        1021.2466666666666,
        1007.0466666666666
      ],
      "clusters_text": [
        [
          "That",
          "That",
          "That"
        ],
        [
          "<brev-y>th</brev-y><sl>e</sl>",
          "<brev-y>th</brev-y><sl>e</sl>",
          "<brev-y>th</brev-y><sl>e"
        ],
        [
          "ffrench",
          "ffrench",
          "</sl>ffrench"
        ],
        [
          "dye",
          "dye",
          "dye"
        ],
        [
          "Daily",
          "Daily",
          "daily"
        ],
        [
          "of",
          "of",
          "of"
        ],
        [
          "a",
          "a",
          "a"
        ],
        [
          "fflux",
          "fflux",
          "fflux"
        ],
        [
          "-",
          "-",
          "-"
        ],
        [
          "they",
          "They",
          "They"
        ],
        [
          "write",
          "write",
          "write"
        ]
      ],
      "number_views": 3,
      "consensus_score": 2.6363636363636362,
      "consensus_text": "That <brev-y>th</brev-y><sl>e</sl> ffrench dye Daily of a fflux - They write",
      "line_slope": -0.6127575449941545,
      "slope_label": 0,
      "gutter_label": 1,
      "gold_standard": [
        false,
        false,
        false
      ],
      "extract_index": [
        19,
        19,
        0
      ],
      "user_ids": [
        null,
        429539.0,
        1708223.0
      ],
      "low_consensus": true
    },
    {
      "clusters_x": [
        107.64500000000001,
        927.56
      ],
      "clusters_y": [
        1083.01,
        1065.13
      ],
      "clusters_text": [
        [
          "from",
          "from"
        ],
        [
          "Paris",
          "Paris"
        ],
        [
          "that",
          "that"
        ],
        [
          "the",
          "the"
        ],
        [
          "ffrench",
          "ffrench"
        ],
        [
          "King",
          "King"
        ],
        [
          "has",
          "has"
        ],
        [
          "ordered",
          "ordered"
        ]
      ],
      "number_views": 2,
      "consensus_score": 2.0,
      "consensus_text": "from Paris that the ffrench King has ordered",
      "line_slope": -0.6127575449941545,
      "slope_label": 0,
      "gutter_label": 1,
      "gold_standard": [
        false,
        false
      ],
      "extract_index": [
        20,
        18
      ],
      "user_ids": [
        429539.0,
        1708223.0
      ],
      "low_consensus": true
    },
    {
      "clusters_x": [
        108.52333333333333,
        916.0266666666666
      ],
      "clusters_y": [
        1145.9033333333334,
        1124.1933333333334
      ],
      "clusters_text": [
        [
          "a",
          "a",
          "a"
        ],
        [
          "large",
          "large",
          "large"
        ],
        [
          "River",
          "River",
          "River"
        ],
        [
          "to",
          "to",
          "to"
        ],
        [
          "be",
          "be",
          "be"
        ],
        [
          "Cut",
          "Cut",
          "Cut"
        ],
        [
          "from",
          "from",
          "from"
        ],
        [
          "Dunkirk",
          "Dunkirk",
          "Dunkirk"
        ],
        [
          "to",
          "to",
          "to"
        ]
      ],
      "number_views": 3,
      "consensus_score": 3.0,
      "consensus_text": "a large River to be Cut from Dunkirk to",
      "line_slope": -0.6127575449941545,
      "slope_label": 0,
      "gutter_label": 1,
      "gold_standard": [
        false,
        false,
        false
      ],
      "extract_index": [
        21,
        21,
        19
      ],
      "user_ids": [
        null,
        429539.0,
        1708223.0
      ],
      "low_consensus": false
    },
    {
      "clusters_x": [
        107.34333333333332,
        922.9066666666668
      ],
      "clusters_y": [
        1208.1533333333334,
        1191.3999999999999
      ],
      "clusters_text": [
        [
          "Graveling",
          "Graveling",
          "Graveling"
        ],
        [
          "-",
          "-",
          "-"
        ],
        [
          "from",
          "from",
          "from"
        ],
        [
          "the",
          "the",
          "the"
        ],
        [
          "Hague",
          "Hague",
          "Hague"
        ],
        [
          "that",
          "that",
          "that"
        ],
        [
          "the",
          "the",
          "the"
        ],
        [
          "states",
          "states",
          "States"
        ]
      ],
      "number_views": 3,
      "consensus_score": 2.875,
      "consensus_text": "Graveling - from the Hague that the states",
      "line_slope": -0.6127575449941545,
      "slope_label": 0,
      "gutter_label": 1,
      "gold_standard": [
        false,
        false,
        false
      ],
      "extract_index": [
        22,
        22,
        20
      ],
      "user_ids": [
        null,
        429539.0,
        1708223.0
      ],
      "low_consensus": true
    },
    {
      "clusters_x": [
        106.695,
        929.08
      ],
      "clusters_y": [
        1272.745,
        1249.295
      ],
      "clusters_text": [
        [
          "Generall",
          "Generall"
        ],
        [
          "will",
          "will"
        ],
        [
          "make",
          "make"
        ],
        [
          "another",
          "another"
        ],
        [
          "Reforme",
          "Reforme"
        ],
        [
          "of",
          "of"
        ]
      ],
      "number_views": 2,
      "consensus_score": 2.0,
      "consensus_text": "Generall will make another Reforme of",
      "line_slope": -0.6127575449941545,
      "slope_label": 0,
      "gutter_label": 1,
      "gold_standard": [
        false,
        false
      ],
      "extract_index": [
        23,
        21
      ],
      "user_ids": [
        429539.0,
        1708223.0
      ],
      "low_consensus": true
    },
    {
      "clusters_x": [
        104.28666666666668,
        932.4633333333333
      ],
      "clusters_y": [
        1320.4966666666667,
        1309.3799999999999
      ],
      "clusters_text": [
        [
          "the",
          "the",
          "the"
        ],
        [
          "scotch",
          "scotch",
          "Scotch"
        ],
        [
          "Guards",
          "Guards",
          "Guards"
        ],
        [
          "in",
          "in",
          "in"
        ],
        [
          "their",
          "their",
          "their"
        ],
        [
          "service",
          "service",
          "Service"
        ],
        [
          "-",
          "-",
          "-"
        ],
        [
          "that",
          "That",
          "That"
        ],
        [
          "the",
          "the",
          "the"
        ]
      ],
      "number_views": 3,
      "consensus_score": 2.6666666666666665,
      "consensus_text": "the scotch Guards in their service - That the",
      "line_slope": -0.6127575449941545,
      "slope_label": 0,
      "gutter_label": 1,
      "gold_standard": [
        false,
        false,
        false
      ],
      "extract_index": [
        24,
        24,
        22
      ],
      "user_ids": [
        null,
        429539.0,
        1708223.0
      ],
      "low_consensus": true
    },
    {
      "clusters_x": [
        109.265,
        938.565
      ],
      "clusters_y": [
        1384.0900000000001,
        1372.835
      ],
      "clusters_text": [
        [
          "young",
          "young"
        ],
        [
          "Earle",
          "Earle"
        ],
        [
          "of",
          "of"
        ],
        [
          "Essex",
          "Essex"
        ],
        [
          "who",
          "who"
        ],
        [
          "is",
          "is"
        ],
        [
          "lately",
          "lately"
        ],
        [
          "Arrived",
          "Arrived"
        ],
        [
          "here",
          "here"
        ]
      ],
      "number_views": 2,
      "consensus_score": 2.0,
      "consensus_text": "young Earle of Essex who is lately Arrived here",
      "line_slope": -0.6127575449941545,
      "slope_label": 0,
      "gutter_label": 1,
      "gold_standard": [
        false,
        false
      ],
      "extract_index": [
        25,
        23
      ],
      "user_ids": [
        429539.0,
        1708223.0
      ],
      "low_consensus": true
    },
    {
      "clusters_x": [
        109.49,
        924.2933333333334
      ],
      "clusters_y": [
        1434.7366666666667,
        1421.5600000000002
      ],
      "clusters_text": [
        [
          "from",
          "from",
          "from"
        ],
        [
          "England",
          "England",
          "England"
        ],
        [
          "will",
          "will",
          "will"
        ],
        [
          "set",
          "set",
          "set"
        ],
        [
          "out",
          "out",
          "out"
        ],
        [
          "in",
          "in",
          "in"
        ],
        [
          "few",
          "few",
          "few"
        ],
        [
          "Dayes",
          "Dayes",
          "Dayes"
        ],
        [
          "on",
          "on",
          "on"
        ]
      ],
      "number_views": 3,
      "consensus_score": 3.0,
      "consensus_text": "from England will set out in few Dayes on",
      "line_slope": -0.6127575449941545,
      "slope_label": 0,
      "gutter_label": 1,
      "gold_standard": [
        false,
        false,
        false
      ],
      "extract_index": [
        26,
        26,
        24
      ],
      "user_ids": [
        null,
        429539.0,
        1708223.0
      ],
      "low_consensus": false
    },
    {
      "clusters_x": [
        99.185,
        934.36
      ],
      "clusters_y": [
        1480.325,
        1465.0
      ],
      "clusters_text": [
        [
          "his",
          "his"
        ],
        [
          "Jntended",
          "Intended"
        ],
        [
          "Travells",
          "Travells"
        ],
        [
          "through",
          "through"
        ],
        [
          "Jtaly",
          "Italy"
        ],
        [
          "<sw-ex>et</sw-ex>c",
          "&c."
        ],
        [
          "-",
          ""
        ]
      ],
      "number_views": 2,
      "consensus_score": 1.4285714285714286,
      "consensus_text": "his Jntended Travells through Jtaly <sw-ex>et</sw-ex>c -",
      "line_slope": -0.6127575449941545,
      "slope_label": 0,
      "gutter_label": 1,
      "gold_standard": [
        false,
        false
      ],
      "extract_index": [
        27,
        27
      ],
      "user_ids": [
        null,
        429539.0
      ],
      "low_consensus": true
    }
  ],
  "low_consensus_lines": 24,
  "transcribed_lines": 26,
  "reducer": "poly_line_text_reducer",
  "aggregation_version": "3.4.3",
  "parameters": {
    "eps_slope": 0.5,
    "eps_line": 5.0,
    "eps_word": 30.0,
    "gutter_tol": 30.0,
    "min_word_count": 1,
    "dot_freq": "line",
    "min_samples": 2,
    "low_consensus_threshold": 3,
    "minimum_views": 5,
    "process_by_line": false
  }
}