{
  "frame0": [
    {
      "clusters_x": [
        282.99,
        880.5899999999999
      ],
      "clusters_y": [
        73.405,
        80.94999999999999
      ],
      "clusters_text": [
        [
          "London",
          "London"
        ],
        [
          "August",
          "August"
        ],
        [
          "19<sw-sup>th</sw-sup>",
          "14th."
        ],
        [
          "1714",
          "1714"
        ]
      ],
      "number_views": 2,
      "consensus_score": 1.75,
      "consensus_text": "London August 19<sw-sup>th</sw-sup> 1714",
      "line_slope": 0.7273524973413821,
      "slope_label": 1,
      "gutter_label": 0,
      "gold_standard": [
        false,
        false
      ],
      "extract_index": [
        0,
        1
      ],
      "user_ids": [
        1708223.0,
        null
      ],
      "low_consensus": true
    },
    {
      "clusters_x": [
        131.66,
        942.635
      ],
      "clusters_y": [
        237.9,
        218.96499999999997
      ],
      "clusters_text": [
        [
          "their",
          "their"
        ],
        [
          "Humble",
          "Humble"
        ],
        [
          "Thanks",
          "Thanks"
        ],
        [
          "be",
          "be"
        ],
        [
          "Returned",
          "Returned"
        ],
        [
          "to",
          "to"
        ]
      ],
      "number_views": 2,
      "consensus_score": 2.0,
      "consensus_text": "their Humble Thanks be Returned to",
      "line_slope": -1.4615817081787708,
      "slope_label": 0,
      "gutter_label": 0,
      "gold_standard": [
        false,
        false
      ],
      "extract_index": [
        2,
        3
      ],
      "user_ids": [
        1708223.0,
        null
      ],
      "low_consensus": true
    },
    {
      "clusters_x": [
        127.31,
        937.54
      ],
      "clusters_y": [
        300.08000000000004,
        290.205
      ],
      "clusters_text": [
        [
          "his",
          "his"
        ],
        [
          "Majesty",
          "Majesty"
        ],
        [
          "for",
          "for"
        ],
        [
          "his",
          "his"
        ],
        [
          "Grace",
          "Grace"
        ],
        [
          "and",
          "and"
        ],
        [
          "Goodness",
          "Goodness"
        ]
      ],
      "number_views": 2,
      "consensus_score": 2.0,
      "consensus_text": "his Majesty for his Grace and Goodness",
      "line_slope": -1.4615817081787708,
      "slope_label": 0,
      "gutter_label": 0,
      "gold_standard": [
        false,
        false
      ],
      "extract_index": [
        15,
        4
      ],
      "user_ids": [
        1779578.0,
        null
      ],
      "low_consensus": true
    },
    {
      "clusters_x": [
        124.07,
        948.7
      ],
      "clusters_y": [
        372.425,
        350.495
      ],
      "clusters_text": [
        [
          "to",
          "to"
        ],
        [
          "his",
          "his"
        ],
        [
          "people",
          "People"
        ],
        [
          "Expressed",
          "Expressed"
        ],
        [
          "in",
          "in"
        ],
        [
          "his",
          "his"
        ],
        [
          "Letter",
          "Letter"
        ],
        [
          "to",
          "to"
        ]
      ],
      "number_views": 2,
      "consensus_score": 1.875,
      "consensus_text": "to his people Expressed in his Letter to",
      "line_slope": -1.4615817081787708,
      "slope_label": 0,
      "gutter_label": 0,
      "gold_standard": [
        false,
        false
      ],
      "extract_index": [
        14,
        5
      ],
      "user_ids": [
        1779578.0,
        null
      ],
      "low_consensus": true
    },
    {
      "clusters_x": [
        123.82000000000001,
        940.48
      ],
      "clusters_y": [
        446.02,
        418.8
      ],
      "clusters_text": [
        [
          "the",
          "the",
          "the"
        ],
        [
          "Lords",
          "Lord",
          "Lords"
        ],
        [
          "Justices",
          "Justice",
          "Justices"
        ],
        [
          "with",
          "with",
          "with"
        ],
        [
          "the",
          "the",
          "the"
        ],
        [
          "Assurance",
          "Assurance",
          "Assurance"
        ]
      ],
      "number_views": 3,
      "consensus_score": 2.6666666666666665,
      "consensus_text": "the Lords Justices with the Assurance",
      "line_slope": -1.4615817081787708,
      "slope_label": 0,
      "gutter_label": 0,
      "gold_standard": [
        false,
        false,
        false
      ],
      "extract_index": [
        13,
        7,
        6
      ],
      "user_ids": [
        1779578.0,
        1708223.0,
        null
      ],
      "low_consensus": true
    },
    {
      "clusters_x": [
        121.44333333333333,
        940.8066666666667
      ],
      "clusters_y": [
        520.6033333333334,
        493.51
      ],
      "clusters_text": [
        [
          "of",
          "of",
          "of"
        ],
        [
          "their",
          "their",
          "their"
        ],
        [
          "fidelity",
          "fidelity",
          "fidelity"
        ],
        [
          "and",
          "and",
          "and"
        ],
        [
          "<sw-unclear>zeales</sw-unclear>",
          "Zeale",
          "Zeale"
        ],
        [
          "of",
          "of",
          "of"
        ],
        [
          "this",
          "this",
          "this"
        ],
        [
          "House",
          "House",
          "House"
        ]
      ],
      "number_views": 3,
      "consensus_score": 2.875,
      "consensus_text": "of their fidelity and Zeale of this House",
      "line_slope": -1.4615817081787708,
      "slope_label": 0,
      "gutter_label": 0,
      "gold_standard": [
        false,
        false,
        false
      ],
      "extract_index": [
        11,
        8,
        7
      ],
      "user_ids": [
        1779578.0,
        1708223.0,
        null
      ],
      "low_consensus": true
    },
    {
      "clusters_x": [
        132.26666666666668,
        935.7766666666666
      ],
      "clusters_y": [
        588.55,
        570.6533333333333
      ],
      "clusters_text": [
        [
          "for",
          "for",
          "for"
        ],
        [
          "his",
          "his",
          "his"
        ],
        [
          "Majestyes",
          "Ma<sw-ex>ies</sw-ex><sl>tie</sl>s",
          "Majestyes"
        ],
        [
          "service",
          "Service",
          "Service"
        ],
        [
          "-",
          "-",
          "-"
        ],
        [
          "Ordered",
          "Ordered",
          "Ordered"
        ],
        [
          "that",
          "that",
          "that"
        ]
      ],
      "number_views": 3,
      "consensus_score": 2.7142857142857144,
      "consensus_text": "for his Majestyes Service - Ordered that",
      "line_slope": -1.4615817081787708,
      "slope_label": 0,
      "gutter_label": 0,
      "gold_standard": [
        false,
        false,
        false
      ],
      "extract_index": [
        12,
        6,
        8
      ],
      "user_ids": [
        1779578.0,
        1708223.0,
        null
      ],
      "low_consensus": true
    },
    {
      "clusters_x": [
        123.915,
        932.56
      ],
      "clusters_y": [
        658.185,
        644.8
      ],
      "clusters_text": [
        [
          "the",
          "the"
        ],
        [
          "Lord",
          "Lord"
        ],
        [
          "Chancellor",
          "Chancellor"
        ],
        [
          "doe",
          "doe"
        ],
        [
          "lay",
          "lay"
        ],
        [
          "the",
          "the"
        ],
        [
          "said",
          "said"
        ]
      ],
      "number_views": 2,
      "consensus_score": 2.0,
      "consensus_text": "the Lord Chancellor doe lay the said",
      "line_slope": -1.4615817081787708,
      "slope_label": 0,
      "gutter_label": 0,
      "gold_standard": [
        false,
        false
      ],
      "extract_index": [
        9,
        9
      ],
      "user_ids": [
        1779578.0,
        null
      ],
      "low_consensus": true
    },
    {
      "clusters_x": [
        122.28333333333335,
        923.3633333333333
      ],
      "clusters_y": [
        728.7066666666666,
        716.7933333333334
      ],
      "clusters_text": [
        [
          "Resolution",
          "Resolution",
          "Resolution"
        ],
        [
          "before",
          "before",
          "before"
        ],
        [
          "the",
          "the",
          "the"
        ],
        [
          "Lords",
          "Lord",
          "Lords"
        ],
        [
          "Justices",
          "Justice",
          "Justices"
        ]
      ],
      "number_views": 3,
      "consensus_score": 2.6,
      "consensus_text": "Resolution before the Lords Justices",
      "line_slope": -1.4615817081787708,
      "slope_label": 0,
      "gutter_label": 0,
      "gold_standard": [
        false,
        false,
        false
      ],
      "extract_index": [
        10,
        5,
        10
      ],
      "user_ids": [
        1779578.0,
        1708223.0,
        null
      ],
      "low_consensus": true
    },
    {
      "clusters_x": [
        127.38,
        911.84
      ],
      "clusters_y": [
        797.2750000000001,
        784.38
      ],
      "clusters_text": [
        [
          "to",
          "to"
        ],
        [
          "Transmit",
          "Transmit"
        ],
        [
          "the",
          "the"
        ],
        [
          "same",
          "same"
        ],
        [
          "to",
          "to"
        ],
        [
          "the",
          "the"
        ],
        [
          "King",
          "King"
        ]
      ],
      "number_views": 2,
      "consensus_score": 2.0,
      "consensus_text": "to Transmit the same to the King",
      "line_slope": -1.4615817081787708,
      "slope_label": 0,
      "gutter_label": 0,
      "gold_standard": [
        false,
        false
      ],
      "extract_index": [
        20,
        11
      ],
      "user_ids": [
        1779578.0,
        null
      ],
      "low_consensus": true
    },
    {
      "clusters_x": [
        126.23,
        926.87
      ],
      "clusters_y": [
        876.3566666666666,
        860.3533333333334
      ],
      "clusters_text": [
        [
          "with",
          "with",
          "with"
        ],
        [
          "all",
          "all",
          "all"
        ],
        [
          "Convenient",
          "Convenient",
          "Convenient"
        ],
        [
          "speed",
          "Speed",
          "Speed"
        ],
        [
          "-",
          "-",
          "-"
        ],
        [
          "The",
          "the",
          "The"
        ],
        [
          "Comm-",
          "Commons",
          "Com"
        ]
      ],
      "number_views": 3,
      "consensus_score": 2.4285714285714284,
      "consensus_text": "with all Convenient Speed - The Comm-",
      "line_slope": -1.4615817081787708,
      "slope_label": 0,
      "gutter_label": 0,
      "gold_standard": [
        false,
        false,
        false
      ],
      "extract_index": [
        8,
        10,
        12
      ],
      "user_ids": [
        1779578.0,
        1708223.0,
        null
      ],
      "low_consensus": true
    },
    {
      "clusters_x": [
        123.375,
        941.2
      ],
      "clusters_y": [
        947.175,
        925.9649999999999
      ],
      "clusters_text": [
        [
          "mons",
          "=mons"
        ],
        [
          "also",
          "also"
        ],
        [
          "Voted",
          "Voted"
        ],
        [
          "to",
          "to"
        ],
        [
          "<sw-unclear>Re????</sw-unclear>",
          "Returne"
        ],
        [
          "their",
          "their"
        ],
        [
          "Hum-",
          "Hum"
        ]
      ],
      "number_views": 2,
      "consensus_score": 1.5714285714285714,
      "consensus_text": "mons also Voted to <sw-unclear>Re????</sw-unclear> their Hum-",
      "line_slope": -1.4615817081787708,
      "slope_label": 0,
      "gutter_label": 0,
      "gold_standard": [
        false,
        false
      ],
      "extract_index": [
        7,
        13
      ],
      "user_ids": [
        1779578.0,
        null
      ],
      "low_consensus": true
    },
    {
      "clusters_x": [
        120.82,
        927.5799999999999
      ],
      "clusters_y": [
        1009.76,
        989.48
      ],
      "clusters_text": [
        [
          "ble",
          "=ble"
        ],
        [
          "thanks",
          "Thanks"
        ],
        [
          "&<sw-sup>c</sw-sup>",
          "&<sw-sup>c</sw-sup>."
        ],
        [
          "to",
          "to"
        ],
        [
          "the",
          "the"
        ],
        [
          "same",
          "same"
        ],
        [
          "Effect",
          "Effect"
        ],
        [
          "",
          "-"
        ]
      ],
      "number_views": 2,
      "consensus_score": 1.5,
      "consensus_text": "ble thanks &<sw-sup>c</sw-sup> to the same Effect -",
      "line_slope": -1.4615817081787708,
      "slope_label": 0,
      "gutter_label": 0,
      "gold_standard": [
        false,
        false
      ],
      "extract_index": [
        6,
        14
      ],
      "user_ids": [
        1779578.0,
        null
      ],
      "low_consensus": true
    },
    {
      "clusters_x": [
        114.185,
        936.295
      ],
      "clusters_y": [
        1080.65,
        1065.37
      ],
      "clusters_text": [
        [
          "Leiutenant",
          "Leivtenant"
        ],
        [
          "Gonerall",
          "Generall"
        ],
        [
          "Witham",
          "Witham"
        ],
        [
          "is",
          "is"
        ],
        [
          "Ordered",
          "Ordered"
        ]
      ],
      "number_views": 2,
      "consensus_score": 1.6,
      "consensus_text": "Leiutenant Gonerall Witham is Ordered",
      "line_slope": -1.4615817081787708,
      "slope_label": 0,
      "gutter_label": 0,
      "gold_standard": [
        false,
        false
      ],
      "extract_index": [
        4,
        15
      ],
      "user_ids": [
        1779578.0,
        null
      ],
      "low_consensus": true
    },
    {
      "clusters_x": [
        113.1,
        941.925
      ],
      "clusters_y": [
        1159.15,
        1131.395
      ],
      "clusters_text": [
        [
          "by",
          "by"
        ],
        [
          "<brev-y>th</brev-y><sl>e</sl>",
          "<brev-y>th</brev-y><sl>e</sl>"
        ],
        [
          "Lords",
          "Lords"
        ],
        [
          "Justicies",
          "Justices"
        ],
        [
          "down",
          "Down"
        ],
        [
          "to",
          "to"
        ],
        [
          "North",
          "North"
        ],
        [
          "Brit",
          "Brit="
        ]
      ],
      "number_views": 2,
      "consensus_score": 1.625,
      "consensus_text": "by <brev-y>th</brev-y><sl>e</sl> Lords Justicies down to North Brit",
      "line_slope": -1.4615817081787708,
      "slope_label": 0,
      "gutter_label": 0,
      "gold_standard": [
        false,
        false
      ],
      "extract_index": [
        5,
        16
      ],
      "user_ids": [
        1779578.0,
        null
      ],
      "low_consensus": true
    },
    {
      "clusters_x": [
        124.17999999999999,
        922.725
      ],
      "clusters_y": [
        1233.85,
        1208.1399999999999
      ],
      "clusters_text": [
        [
          "tain",
          ""
        ],
        [
          "to",
          "to"
        ],
        [
          "Command",
          "Command"
        ],
        [
          "the",
          "the"
        ],
        [
          "troopes",
          "Troops"
        ],
        [
          "in",
          "in"
        ],
        [
          "those",
          "those"
        ]
      ],
      "number_views": 2,
      "consensus_score": 1.7142857142857142,
      "consensus_text": "tain to Command the troopes in those",
      "line_slope": -1.4615817081787708,
      "slope_label": 0,
      "gutter_label": 0,
      "gold_standard": [
        false,
        false
      ],
      "extract_index": [
        22,
        14
      ],
      "user_ids": [
        1779578.0,
        1708223.0
      ],
      "low_consensus": true
    },
    {
      "clusters_x": [
        107.465,
        938.8199999999999
      ],
      "clusters_y": [
        1309.105,
        1273.7350000000001
      ],
      "clusters_text": [
        [
          "parts",
          "parts"
        ],
        [
          "-",
          "-"
        ],
        [
          "",
          "It"
        ],
        [
          "this",
          "is"
        ],
        [
          "said",
          "said"
        ],
        [
          "that",
          "that"
        ],
        [
          "20000",
          "20000"
        ],
        [
          "Men",
          "Men"
        ],
        [
          "are",
          "are"
        ],
        [
          "to",
          "to"
        ],
        [
          "be",
          "be"
        ]
      ],
      "number_views": 2,
      "consensus_score": 1.8181818181818181,
      "consensus_text": "parts - It this said that 20000 Men are to be",
      "line_slope": -1.4615817081787708,
      "slope_label": 0,
      "gutter_label": 0,
      "gold_standard": [
        false,
        false
      ],
      "extract_index": [
        0,
        18
      ],
      "user_ids": [
        1779578.0,
        null
      ],
      "low_consensus": true
    },
    {
      "clusters_x": [
        110.33500000000001,
        951.865
      ],
      "clusters_y": [
        1369.01,
        1342.98
      ],
      "clusters_text": [
        [
          "kept",
          "Kept"
        ],
        [
          "and",
          "and"
        ],
        [
          "maintained",
          "Maintained"
        ],
        [
          "on",
          "on"
        ],
        [
          "the",
          "the"
        ],
        [
          "Establishment",
          "Establishment"
        ]
      ],
      "number_views": 2,
      "consensus_score": 1.6666666666666667,
      "consensus_text": "kept and maintained on the Establishment",
      "line_slope": -1.4615817081787708,
      "slope_label": 0,
      "gutter_label": 0,
      "gold_standard": [
        false,
        false
      ],
      "extract_index": [
        1,
        19
      ],
      "user_ids": [
        1779578.0,
        null
      ],
      "low_consensus": true
    },
    {
      "clusters_x": [
        115.10499999999999,
        940.145
      ],
      "clusters_y": [
        1435.0749999999998,
        1397.5500000000002
      ],
      "clusters_text": [
        [
          "in",
          "in"
        ],
        [
          "Ireland",
          "Ireland"
        ],
        [
          "for",
          "for"
        ],
        [
          "<brev-y>th</brev-y><sl>e</sl>",
          "<brev-y>th</brev-y><sl>e</sl>"
        ],
        [
          "Security",
          "Security"
        ],
        [
          "of",
          "of"
        ],
        [
          "<brev-y>th</brev-y><sl>e</sl>",
          "<brev-y>th</brev-y><sw-ex>a</sw-ex><sl>t</sl>"
        ],
        [
          "Kingdom",
          "Kingdom"
        ],
        [
          "and",
          "and"
        ]
      ],
      "number_views": 2,
      "consensus_score": 1.8888888888888888,
      "consensus_text": "in Ireland for <brev-y>th</brev-y><sl>e</sl> Security of <brev-y>th</brev-y><sl>e</sl> Kingdom and",
      "line_slope": -1.4615817081787708,
      "slope_label": 0,
      "gutter_label": 0,
      "gold_standard": [
        false,
        false
      ],
      "extract_index": [
        2,
        20
      ],
      "user_ids": [
        1779578.0,
        null
      ],
      "low_consensus": true
    },
    {
      "clusters_x": [
        114.36,
        928.76
      ],
      "clusters_y": [
        1489.605,
        1469.725
      ],
      "clusters_text": [
        [
          "all",
          "all"
        ],
        [
          "Papists",
          "Papists"
        ],
        [
          "<sw-ex>and</sw-ex>",
          "&"
        ],
        [
          "Nonjurors",
          "Nonjurors"
        ],
        [
          "are",
          "are"
        ],
        [
          "to",
          "to"
        ],
        [
          "be",
          "be"
        ],
        [
          "disarmed",
          "Disarmed"
        ]
      ],
      "number_views": 2,
      "consensus_score": 1.75,
      "consensus_text": "all Papists <sw-ex>and</sw-ex> Nonjurors are to be disarmed",
      "line_slope": -1.4615817081787708,
      "slope_label": 0,
      "gutter_label": 0,
      "gold_standard": [
        false,
        false
      ],
      "extract_index": [
        3,
        21
      ],
      "user_ids": [
        1779578.0,
        null
      ],
      "low_consensus": true
    }
  ],
  "low_consensus_lines": 20,
  "transcribed_lines": 20,
  "reducer": "poly_line_text_reducer",
  "aggregation_version": "3.4.3",
  "parameters": {
    "eps_slope": 0.5,
    "eps_line": 5.0,
    "eps_word": 30.0,
    "gutter_tol": 30.0,
    "min_word_count": 1,
    "dot_freq": "line",
    "min_samples": 2,
    "low_consensus_threshold": 3,
    "minimum_views": 5,
    "process_by_line": false
  }
}